{
  "name": "Cordelia Vargas",
  "age": 48,
  "address": {
    "street": "Uswi Terrace",
    "city": "Vacerwa",
    "state": "ME",
    "zip": "41805"
  },
  "contact": {
    "phone": "(883) 218-7746",
    "servicePhone": "800679471"
  },
  "birthday": "1978-09-19T00:21:45.784Z",
  "ip": "16.9.108.248",
  "foo": "bar",
  "profile": {
    "about": "Faz diwme ralmi hi wajeigi zowonte juwuluvuf fazna rib idupelup ew jeni acaka ote tasu duv. Wudofuw tujanof ravudne josbuna gegvibje luc lircakco eg iveogunog liwatom soze tehjobez. Zorep arowiwugi gehoffar pidok teulke upmeab elhewcu ivavos kifok agpozo ov gi ojnas wolsin acehof ke. Got zokkob woz nap lorogluk nuhkicsu cigi riazohog ajrowir naw nok ki datampet cawovzes besigijed zuehupo ebnad. Nehge va iwetubdec fezizadef oc he mezo sohvecgo wuf uw nehebup gakca. Vu ono muk ownufbig eveagi huso hoh gilwarla lilduku hokfu dofle mabehti moz wil.",
    "bio": "Cijak cujisivet am ligsiuw urize vasittu gap fitlo jaj ge mevodvoz etugug. Okicacel gi dohte ijpes hek tazosbe cu baspeso jijlihir kevu be vod noblegar owe. Bi lacfi ef muh ferewaf zu hunakac dalajpup pud diiggaf odi we houk tesulas. Dafukzo bor wi lijtasvup jazmo kilsom galezmu jazkumde gul nebca jeezemaf ekapi zahelje ejifor naetafa podosfo re. Gocowefa kecpodgor gip hemi sifa bumi puhfewe re ef at izeve ivonone hi tih faghu re dahbaz. Tolo kucartol mukeg doc wu wokcukzan covsa jebihgu gak kizo go je. Sami seulo owfizol faguco ca daabofab wu oduvemtet udidaped kame ropvu rimifule."
  },
  "apiKey": "ede6ce12d9b16929eed2578b3caa08f861c658796cb0d84cacedfae86a89907b",
  "currency": {
    "code": "GGP",
    "name": "Guernsey Pound"
  }
}